testingproject/__init__.py
testingproject-1.0.dist-info/METADATA
testingproject-1.0.dist-info/WHEEL
testingproject-1.0.dist-info/top_level.txt
testingproject-1.0.dist-info/RECORD
